kamino/__init__.py
kamino/__main__.py
kamino/cli/__init__.py
kamino/cli/init.py
kamino/cli/run.py
kamino/constants.py
kamino/core/init_configuration.py
kamino/core/load_configuration.py
kamino/core/load_repository.py
kamino/core/replace_tags.py
kamino/core/respository/Directory.py
kamino/core/respository/File.py
kamino/core/respository/Repository.py
kamino/core/respository/__init__.py
kamino/core/save_repository.py
kamino/core/traverse_directory.py
kamino-1.0.0.dist-info/WHEEL
kamino-1.0.0.dist-info/METADATA
kamino-1.0.0.dist-info/RECORD
