Metadata-Version: 2.1
Name: kamino
Version: 1.0.0
Summary: Kamino is a simple and easy to use replication tool. With focus do made easier apps replications
Author: Samuel Nogueira Bacelar
Author-email: samuelnbacelar@hotmail.com
Requires-Python: >=3.10,<4.0
Classifier: Programming Language :: Python :: 3
Classifier: Programming Language :: Python :: 3.10
Requires-Dist: jsonschema (>=4.9.1,<5.0.0)
